cameo_future/__init__.py
cameo_future/cameo_future.py
cameo_future-0.1.0.dist-info/METADATA
cameo_future-0.1.0.dist-info/WHEEL
cameo_future-0.1.0.dist-info/top_level.txt
cameo_future-0.1.0.dist-info/RECORD
