Metadata-Version: 2.1
Name: cameo-future
Version: 0.1.0
Summary: Cameo Future predict future.
Home-page: https://github.com/bohachu/cameo_future
Author: Bowen Chiu
Author-email: cbh@cameo.tw
License: UNKNOWN
Platform: UNKNOWN
Classifier: Programming Language :: Python :: 3
Classifier: License :: OSI Approved :: MIT License
Classifier: Operating System :: OS Independent
